genie_git/__init__.py
genie_git/ai_handler.py
genie_git/cli.py
genie_git/cli_handlers.py
genie_git/config.py
genie_git/git_handler.py
genie_git/main.py
genie_git-0.2.0.dist-info/WHEEL
genie_git-0.2.0.dist-info/entry_points.txt
genie_git-0.2.0.dist-info/METADATA
genie_git-0.2.0.dist-info/RECORD
