Metadata-Version: 2.3
Name: genie-git
Version: 0.2.0
Summary: An AI-powered tool to suggest conventional git commit messages.
Author: Majed Lutfi
Author-email: Majed Lutfi <majedelutfi@hotmail.com>
License: MIT License
Requires-Dist: gitpython>=3.1.45
Requires-Dist: google-genai>=1.36.0
Requires-Dist: pyperclip>=1.11.0
Requires-Dist: pre-commit>=4.3.0 ; extra == 'dev'
Requires-Dist: pytest>=8.4.2 ; extra == 'dev'
Requires-Dist: pytest-cov>=7.0.0 ; extra == 'dev'
Requires-Dist: pytest-mock>=3.15.1 ; extra == 'dev'
Requires-Python: >=3.12
Provides-Extra: dev
